asciiplot/__init__.py
asciiplot/_asciiization.py
asciiplot/_chart/__init__.py
asciiplot/_chart/grid/__init__.py
asciiplot/_chart/grid/cell.py
asciiplot/_chart/serialized/__init__.py
asciiplot/_chart/serialized/layout_elements.py
asciiplot/_chart/serialized/x_axis_tick_row.py
asciiplot/_coloring.py
asciiplot/_config.py
asciiplot/_constants.py
asciiplot/_params.py
asciiplot/_sequence_interpolation.py
asciiplot/_type_aliases.py
asciiplot/_utils/__init__.py
asciiplot/_utils/console.py
asciiplot/_utils/formatting.py
asciiplot/_utils/iterables.py
asciiplot/_utils/numerical.py
asciiplot-1.0.0.dist-info/WHEEL
asciiplot-1.0.0.dist-info/METADATA
asciiplot-1.0.0.dist-info/LICENSE
asciiplot-1.0.0.dist-info/RECORD
