Metadata-Version: 2.1
Name: asciiplot
Version: 1.0.0
Summary: Platform-agnostic, highly customizable sequence plotting in the console
Home-page: https://github.com/w2sv/asciiplot
License: MIT
Keywords: plotting,terminal,console,ascii,gui,data,visualization,statistics,sequences
Author: w2sv
Author-email: zangenbergjanek@googlemail.com
Requires-Python: >=3.6,<4.0
Classifier: License :: OSI Approved :: MIT License
Classifier: Operating System :: OS Independent
Classifier: Programming Language :: Python :: 3
Classifier: Programming Language :: Python :: 3.6
Classifier: Programming Language :: Python :: 3.7
Classifier: Programming Language :: Python :: 3.8
Classifier: Programming Language :: Python :: 3.9
Classifier: Programming Language :: Python :: 3.10
Classifier: Programming Language :: Python :: 3.11
Classifier: Programming Language :: Python :: 3
Requires-Dist: colored (==1.4.2)
Requires-Dist: dataclasses
Requires-Dist: more-itertools
Project-URL: Repository, https://github.com/w2sv/asciiplot
